Metadata-Version: 1.1
Name: tcramm0nd-udacity-datascience-binomial
Version: 0.0.1
Summary: Gaussian distributions for Udacity Data Science Nandegree
Home-page: https://udacity.com
Author: Tim Crammond
Author-email: author@example.com
License: UNKNOWN
Platform: UNKNOWN
Classifier: Programming Language :: Python :: 3
Classifier: License :: OSI Approved :: MIT License
Classifier: Operating System :: OS Independent
